docs/Makefile
docs/api_reference.rst
docs/conf.py
docs/contributing.rst
docs/history.rst
docs/index.rst
docs/make.bat
docs/readme.rst
docs/sofar.rst
docs/resources/conventions.py
docs/resources/working_with_sofa_HRIR_lateral.png
docs/resources/working_with_sofa_source_horizontal.png
docs/resources/working_with_sofa_source_lateral.png
sofar/__init__.py
sofar/io.py
sofar/sofa.py
sofar/sofastream.py
sofar/update_conventions.py
sofar/utils.py
sofar/sofa_conventions/VERSION
sofar/sofa_conventions/write_upgrade_rules.py
sofar/sofa_conventions/write_verification_data.py
sofar/sofa_conventions/write_verification_rules.py
sofar/sofa_conventions/conventions/AnnotatedEmitterAudio_0.2.csv
sofar/sofa_conventions/conventions/AnnotatedEmitterAudio_0.2.json
sofar/sofa_conventions/conventions/AnnotatedReceiverAudio_0.2.csv
sofar/sofa_conventions/conventions/AnnotatedReceiverAudio_0.2.json
sofar/sofa_conventions/conventions/FreeFieldDirectivityTF_1.1.csv
sofar/sofa_conventions/conventions/FreeFieldDirectivityTF_1.1.json
sofar/sofa_conventions/conventions/FreeFieldHRIR_1.0.csv
sofar/sofa_conventions/conventions/FreeFieldHRIR_1.0.json
sofar/sofa_conventions/conventions/FreeFieldHRTF_1.0.csv
sofar/sofa_conventions/conventions/FreeFieldHRTF_1.0.json
sofar/sofa_conventions/conventions/GeneralFIR-E_2.0.csv
sofar/sofa_conventions/conventions/GeneralFIR-E_2.0.json
sofar/sofa_conventions/conventions/GeneralFIR_1.0.csv
sofar/sofa_conventions/conventions/GeneralFIR_1.0.json
sofar/sofa_conventions/conventions/GeneralSOS_1.0.csv
sofar/sofa_conventions/conventions/GeneralSOS_1.0.json
sofar/sofa_conventions/conventions/GeneralTF-E_1.0.csv
sofar/sofa_conventions/conventions/GeneralTF-E_1.0.json
sofar/sofa_conventions/conventions/GeneralTF_1.0.csv
sofar/sofa_conventions/conventions/GeneralTF_1.0.json
sofar/sofa_conventions/conventions/GeneralTF_2.0.csv
sofar/sofa_conventions/conventions/GeneralTF_2.0.json
sofar/sofa_conventions/conventions/SimpleFreeFieldHRIR_1.0.csv
sofar-1.2.2.dist-info/licenses/LICENSE
sofar-1.2.2.dist-info/METADATA
sofar-1.2.2.dist-info/WHEEL
sofar-1.2.2.dist-info/top_level.txt
sofar-1.2.2.dist-info/RECORD
